tools_tables/__init__.py
tools_tables/modulo.py
read_tables-0.1.6.dist-info/METADATA
read_tables-0.1.6.dist-info/WHEEL
read_tables-0.1.6.dist-info/RECORD
